netbox_sitemaps/__init__.py
netbox_sitemaps/filtersets.py
netbox_sitemaps/forms.py
netbox_sitemaps/models.py
netbox_sitemaps/navigation.py
netbox_sitemaps/tables.py
netbox_sitemaps/urls.py
netbox_sitemaps/views.py
netbox_sitemaps/templates/netbox_sitemaps/sitemaps.html
netbox_sitemaps-0.1.0.dist-info/licenses/LICENSE
netbox_sitemaps-0.1.0.dist-info/METADATA
netbox_sitemaps-0.1.0.dist-info/WHEEL
netbox_sitemaps-0.1.0.dist-info/top_level.txt
netbox_sitemaps-0.1.0.dist-info/RECORD
