Metadata-Version: 2.4
Name: netbox-sitemaps
Version: 0.1.0
Summary: NetBox plugin to display sites on a map.
Author-email: Lars Däschner <contact@ldaeschner.de>
Project-URL: Documentation, https://github.com/Larster05/netbox-sitemaps/blob/main/README.md
Project-URL: Source, https://github.com/Larster05/netbox-sitemaps
Project-URL: Tracker, https://github.com/Larster05/netbox-sitemaps/issues
Classifier: Development Status :: 3 - Alpha
Classifier: Intended Audience :: Developers
Classifier: Natural Language :: English
Classifier: Programming Language :: Python :: 3 :: Only
Classifier: Programming Language :: Python :: 3.10
Classifier: Programming Language :: Python :: 3.11
Classifier: Programming Language :: Python :: 3.12
Requires-Python: >=3.10.0
License-File: LICENSE
Provides-Extra: test
Requires-Dist: black==24.3.0; extra == "test"
Requires-Dist: check-manifest==0.49; extra == "test"
Requires-Dist: flake8; extra == "test"
Requires-Dist: flake8-pyproject; extra == "test"
Requires-Dist: pre-commit==3.7.0; extra == "test"
Requires-Dist: pytest==8.1.1; extra == "test"
Dynamic: license-file
